<?xml version="1.0" encoding="UTF-8" standalone="no"?>
<window xmlns="http://jmix.io/schema/ui/window"
        caption="msg://jobModelBrowse.caption"
        focusComponent="jobModelsTable">
    <data readOnly="true">
        <collection id="jobModelsDc" class="io.jmix.quartz.model.JobModel"/>
    </data>
    <facets>
        <dataLoadCoordinator auto="true"/>
    </facets>
    <actions>
        <action id="lookupSelectAction"
                caption="msg:///actions.Select"
                icon="LOOKUP_OK"
                primary="true"
                shortcut="${COMMIT_SHORTCUT}"/>
        <action id="lookupCancelAction"
                caption="msg:///actions.Cancel"
                icon="LOOKUP_CANCEL"/>
        <action id="applyFilter"
                caption="msg:///actions.Apply"
                icon="font-icon:SEARCH"/>
    </actions>
    <dialogMode height="600"
                width="800"/>
    <layout expand="jobModelsTable" spacing="true">
        <groupBox id="filter" spacing="true" caption="msg:///filter.emptyConfiguration.name" orientation="horizontal"
                  collapsable="true">
            <responsiveGridLayout>
                <row stylename="mt-md-n2">
                    <col md="AUTO" stylename="pl-0 pt-2">
                        <hbox spacing="true" align="MIDDLE_LEFT">
                            <label value="msg://nameContains" align="MIDDLE_LEFT"/>
                            <textField id="nameField"/>
                        </hbox>
                    </col>
                    <col md="AUTO" stylename="pl-0 pt-2">
                        <hbox spacing="true" align="MIDDLE_LEFT">
                            <label value="msg://groupContains" align="MIDDLE_LEFT"/>
                            <textField id="groupField"/>
                        </hbox>
                    </col>
                    <col md="AUTO" stylename="px-0 pt-2">
                        <hbox spacing="true" align="MIDDLE_LEFT" height="100%">
                            <label value="msg://jobState" align="MIDDLE_LEFT"/>
                            <comboBox id="jobStateComboBox"/>
                        </hbox>
                    </col>
                    <col stylename="w-100 pt-2">
                        <button id="applyFilterBtn" action="applyFilter"/>
                    </col>
                </row>
            </responsiveGridLayout>
        </groupBox>
        <groupTable id="jobModelsTable"
                    width="100%"
                    dataContainer="jobModelsDc">
            <actions>
                <action id="create" type="create"/>
                <action id="edit" type="edit"/>
                <action id="remove" type="remove"/>
                <action id="refresh" type="refresh"/>
                <action id="executeNow" caption="msg://io.jmix.quartz.screen.jobs/triggerJob" icon="PLAY_CIRCLE"/>
                <action id="activate" caption="msg://io.jmix.quartz.screen.jobs/resumeJob" icon="PLAY"/>
                <action id="deactivate" caption="msg://io.jmix.quartz.screen.jobs/pauseJob" icon="PAUSE"/>
            </actions>
            <columns>
                <column id="jobName"/>
                <column id="jobGroup" collapsed="true"/>
                <column id="jobClass"/>
                <column id="jobState"/>
                <column id="triggerDescription"/>
                <column id="lastFireDate">
                    <formatter>
                        <date format="msg://dateTimeWithSeconds"/>
                    </formatter>
                </column>
                <column id="nextFireDate">
                    <formatter>
                        <date format="msg://dateTimeWithSeconds"/>
                    </formatter>
                </column>
            </columns>
            <simplePagination/>
            <buttonsPanel id="buttonsPanel"
                          alwaysVisible="true">
                <button id="createBtn" action="jobModelsTable.create"/>
                <button id="editBtn" action="jobModelsTable.edit"/>
                <button id="removeBtn" action="jobModelsTable.remove"/>
                <button id="refreshBtn" action="jobModelsTable.refresh"/>
                <button id="executeNowBtn" action="jobModelsTable.executeNow"/>
                <button id="activateBtn" action="jobModelsTable.activate"/>
                <button id="deactivateBtn" action="jobModelsTable.deactivate"/>
            </buttonsPanel>
        </groupTable>
        <hbox id="lookupActions" spacing="true" visible="false">
            <button action="lookupSelectAction"/>
            <button action="lookupCancelAction"/>
        </hbox>
    </layout>
</window>